pingstats/__init__.py
pingstats/config.py
pingstats/ui.py
pingstats-0.9.4.dist-info/METADATA
pingstats-0.9.4.dist-info/RECORD
pingstats-0.9.4.dist-info/WHEEL
pingstats-0.9.4.dist-info/entry_points.txt
pingstats-0.9.4.dist-info/top_level.txt
pingstats-0.9.4.dist-info/zip-safe
tests/__init__.py
tests/test_init.py
tests/test_ui.py
